cryptolab/__init__.py
cryptolab/cryptolab.py
cryptolab-1.0.1.dist-info/METADATA
cryptolab-1.0.1.dist-info/WHEEL
cryptolab-1.0.1.dist-info/top_level.txt
cryptolab-1.0.1.dist-info/RECORD
