Metadata-Version: 2.4
Name: cryptolab
Version: 1.0.1
Summary: Cryptolab library to replay historic data
Home-page: https://www.crypto-lab.io
Author: CryptoLab, Charles
Author-email: contact@crypto-lab.io
License: MIT
Project-URL: Documentation, https://www.crypto-lab.app/documentation
Project-URL: Source Code, https://github.com/crypto-lab-app/client-libraries
Project-URL: Icon, https://1.gravatar.com/avatar/5121577298f39a1661507198f8615319a7d7a14fad36f9ec52d20ae0d446bf69?size=512
Keywords: cryptolab backtest cryptocurrency cryptocurrencies api bitcoin binance gateio
Requires-Dist: pandas
Requires-Dist: requests
Dynamic: author
Dynamic: author-email
Dynamic: description
Dynamic: description-content-type
Dynamic: home-page
Dynamic: keywords
Dynamic: license
Dynamic: project-url
Dynamic: requires-dist
Dynamic: summary
